clean_links/__init__.py
clean_links/clean.py
clean_links/clearurls.json
clean_links/clearurls_config.json
clean_links/config.py
clean_links/normalize.py
clean_links/unshorten.py
clean_links-0.1.3.dist-info/LICENSE
clean_links-0.1.3.dist-info/METADATA
clean_links-0.1.3.dist-info/WHEEL
clean_links-0.1.3.dist-info/RECORD
