Metadata-Version: 2.1
Name: clean_links
Version: 0.1.3
Summary: Tools for cleaning up links
Home-page: https://github.com/stringertheory/clean-links
Author: Mike Stringer
Author-email: mike.stringer.internet@gmail.com
Requires-Python: >=3.8,<4.0
Classifier: Programming Language :: Python :: 3
Classifier: Programming Language :: Python :: 3.8
Classifier: Programming Language :: Python :: 3.9
Classifier: Programming Language :: Python :: 3.10
Classifier: Programming Language :: Python :: 3.11
Classifier: Programming Language :: Python :: 3.12
Project-URL: Documentation, https://stringertheory.github.io/clean-links/
Project-URL: Repository, https://github.com/stringertheory/clean-links
